{
  "attributes": {
    "sys:address": "काठमाडौं गोकर्णेश्वर नगरपालिका जोरपाटी",
    "sys:age": 48,
    "sys:candidate_id": 335603,
    "sys:center_constituency_id": null,
    "sys:citizenship_district": "काठमाडौं",
    "sys:district": "काठमाडौं",
    "sys:district_code": 26,
    "sys:dob_bs": "2030.11.05",
    "sys:election_year": 2079,
    "sys:experience": "",
    "sys:father_name": "बुद्ध  गिरी",
    "sys:gender": "पुरुष",
    "sys:institute": "",
    "sys:political_party": "राष्ट्रिय प्रजातन्त्र पार्टी",
    "sys:political_party_slug": "raassttriy-prjaatntr-paarttii",
    "sys:qualification": "Masters",
    "sys:rank": "1",
    "sys:remarks": "",
    "sys:sc_constituency_id": "3",
    "sys:serial_no": 1027,
    "sys:spouse_name": "सुनिता  गिरी",
    "sys:state": "बागमती प्रदेश",
    "sys:state_code": 3,
    "sys:symbol_id": 2279,
    "sys:symbol_name": "हलो",
    "sys:votes_received": 2511
  },
  "attributions": [
    "Election Commission Nepal, २०७९ BS election results"
  ],
  "contacts": null,
  "createdAt": "2025-11-04 11:48:36.517999+00:00",
  "description": null,
  "id": "entity:person/gnnesh-girii",
  "identifiers": null,
  "misspelledNames": null,
  "names": [
    {
      "kind": "DEFAULT",
      "lang": "ne",
      "value": "गणेश गिरी"
    }
  ],
  "short_description": null,
  "slug": "gnnesh-girii",
  "subType": null,
  "tags": null,
  "type": "person",
  "versionSummary": {
    "actor": {
      "id": "actor:election-importer",
      "name": "Election Results Importer",
      "slug": "election-importer"
    },
    "changeDescription": "Imported candidate result from election २०७९",
    "createdAt": "2025-11-04 11:48:36.517999+00:00",
    "entityOrRelationshipId": "entity:person/gnnesh-girii",
    "id": "version:entity:person/gnnesh-girii:1",
    "type": "ENTITY",
    "versionNumber": 1
  }
}