{
  "attributes": {
    "sys:address": "बारा पचरौता नगरपालिका श्रीनगर बैरिया",
    "sys:age": 32,
    "sys:candidate_id": 334863,
    "sys:center_constituency_id": null,
    "sys:citizenship_district": "बारा",
    "sys:district": "बारा",
    "sys:district_code": 33,
    "sys:dob_bs": "2046.12.14",
    "sys:election_year": 2079,
    "sys:experience": "",
    "sys:father_name": "राजमंगल प्रसाद यादव",
    "sys:gender": "पुरुष",
    "sys:institute": "",
    "sys:political_party": "स्वतन्त्र",
    "sys:political_party_slug": "independent",
    "sys:qualification": "S.L.C.",
    "sys:rank": "1",
    "sys:remarks": "",
    "sys:sc_constituency_id": "2",
    "sys:serial_no": 1511,
    "sys:spouse_name": "रिन्कु  यादव",
    "sys:state": "मधेश प्रदेश",
    "sys:state_code": 2,
    "sys:symbol_id": 2020,
    "sys:symbol_name": "नेल कटर",
    "sys:votes_received": 27
  },
  "attributions": [
    "Election Commission Nepal, २०७९ BS election results"
  ],
  "contacts": null,
  "createdAt": "2025-11-04 11:48:36.517999+00:00",
  "description": null,
  "id": "entity:person/jitendr-prsaad-yaadv",
  "identifiers": null,
  "misspelledNames": null,
  "names": [
    {
      "kind": "DEFAULT",
      "lang": "ne",
      "value": "जितेन्द्र प्रसाद यादव"
    }
  ],
  "short_description": null,
  "slug": "jitendr-prsaad-yaadv",
  "subType": null,
  "tags": null,
  "type": "person",
  "versionSummary": {
    "actor": {
      "id": "actor:election-importer",
      "name": "Election Results Importer",
      "slug": "election-importer"
    },
    "changeDescription": "Imported candidate result from election २०७९",
    "createdAt": "2025-11-04 11:48:36.517999+00:00",
    "entityOrRelationshipId": "entity:person/jitendr-prsaad-yaadv",
    "id": "version:entity:person/jitendr-prsaad-yaadv:1",
    "type": "ENTITY",
    "versionNumber": 1
  }
}