{
  "attributes": {
    "sys:address": "सुनसरी दुहवी नगरपालिका नया बस्ती",
    "sys:age": 46,
    "sys:candidate_id": 336444,
    "sys:center_constituency_id": null,
    "sys:citizenship_district": "मोरङ्ग",
    "sys:district": "उदयपुर",
    "sys:district_code": 14,
    "sys:dob_bs": "2032.08.29",
    "sys:election_year": 2079,
    "sys:experience": "",
    "sys:father_name": "ओम बहादुर कार्की",
    "sys:gender": "पुरुष",
    "sys:institute": "सरस्वती मावि सुनसरी",
    "sys:political_party": "हाम्रो नेपाली पार्टी",
    "sys:political_party_slug": "haamro-nepaalii-paarttii",
    "sys:qualification": "S.L.C.",
    "sys:rank": "1",
    "sys:remarks": "",
    "sys:sc_constituency_id": "2",
    "sys:serial_no": 434,
    "sys:spouse_name": "सरुना  कार्की",
    "sys:state": "प्रदेश १",
    "sys:state_code": 1,
    "sys:symbol_id": 2319,
    "sys:symbol_name": "लौरो",
    "sys:votes_received": 116
  },
  "attributions": [
    "Election Commission Nepal, २०७९ BS election results"
  ],
  "contacts": null,
  "createdAt": "2025-11-04 11:48:36.517999+00:00",
  "description": null,
  "id": "entity:person/lokendr-bhaadur-kaarkii",
  "identifiers": null,
  "misspelledNames": null,
  "names": [
    {
      "kind": "DEFAULT",
      "lang": "ne",
      "value": "लोकेन्द्र बहादुर कार्की"
    }
  ],
  "short_description": null,
  "slug": "lokendr-bhaadur-kaarkii",
  "subType": null,
  "tags": null,
  "type": "person",
  "versionSummary": {
    "actor": {
      "id": "actor:election-importer",
      "name": "Election Results Importer",
      "slug": "election-importer"
    },
    "changeDescription": "Imported candidate result from election २०७९",
    "createdAt": "2025-11-04 11:48:36.517999+00:00",
    "entityOrRelationshipId": "entity:person/lokendr-bhaadur-kaarkii",
    "id": "version:entity:person/lokendr-bhaadur-kaarkii:1",
    "type": "ENTITY",
    "versionNumber": 1
  }
}