{
  "attributes": {
    "sys:address": "कन्चनपुर सुक्लाफाँटा नगरपालिका आमघाट",
    "sys:age": 56,
    "sys:candidate_id": 338426,
    "sys:center_constituency_id": null,
    "sys:citizenship_district": "दार्चुला",
    "sys:district": "कन्चनपुर",
    "sys:district_code": 75,
    "sys:dob_bs": "2023.02.29",
    "sys:election_year": 2079,
    "sys:experience": "",
    "sys:father_name": "काशी  जोशी",
    "sys:gender": "महिला",
    "sys:institute": "",
    "sys:political_party": "नेपाल मजदुर किसान पार्टी",
    "sys:political_party_slug": "nepaal-mjdur-kisaan-paarttii",
    "sys:qualification": "Education N/A",
    "sys:rank": "1",
    "sys:remarks": "",
    "sys:sc_constituency_id": "1",
    "sys:serial_no": 2346,
    "sys:spouse_name": "गोविन्‍द  जोशी",
    "sys:state": "सुदूरपश्चिम प्रदेश",
    "sys:state_code": 7,
    "sys:symbol_id": 12,
    "sys:symbol_name": "मादल",
    "sys:votes_received": 95
  },
  "attributions": [
    "Election Commission Nepal, २०७९ BS election results"
  ],
  "contacts": null,
  "createdAt": "2025-11-04 11:48:36.517999+00:00",
  "description": null,
  "id": "entity:person/nndaa-devii-joshii",
  "identifiers": null,
  "misspelledNames": null,
  "names": [
    {
      "kind": "DEFAULT",
      "lang": "ne",
      "value": "नन्‍दा देवी जोशी"
    }
  ],
  "short_description": null,
  "slug": "nndaa-devii-joshii",
  "subType": null,
  "tags": null,
  "type": "person",
  "versionSummary": {
    "actor": {
      "id": "actor:election-importer",
      "name": "Election Results Importer",
      "slug": "election-importer"
    },
    "changeDescription": "Imported candidate result from election २०७९",
    "createdAt": "2025-11-04 11:48:36.517999+00:00",
    "entityOrRelationshipId": "entity:person/nndaa-devii-joshii",
    "id": "version:entity:person/nndaa-devii-joshii:1",
    "type": "ENTITY",
    "versionNumber": 1
  }
}