{
  "attributes": {
    "sys:address": "सर्लाही मलंगवा नगरपालिका",
    "sys:age": 28,
    "sys:candidate_id": 337883,
    "sys:center_constituency_id": null,
    "sys:citizenship_district": "सर्लाही",
    "sys:district": "सर्लाही",
    "sys:district_code": 22,
    "sys:dob_bs": "2050.12.03",
    "sys:election_year": 2079,
    "sys:experience": "",
    "sys:father_name": "भोजिन्दर  चौधरी",
    "sys:gender": "पुरुष",
    "sys:institute": "",
    "sys:political_party": "स्वतन्त्र",
    "sys:political_party_slug": "independent",
    "sys:qualification": "s l c",
    "sys:rank": "1",
    "sys:remarks": "",
    "sys:sc_constituency_id": "2",
    "sys:serial_no": 855,
    "sys:spouse_name": "",
    "sys:state": "मधेश प्रदेश",
    "sys:state_code": 2,
    "sys:symbol_id": 2462,
    "sys:symbol_name": "क्रस खुकुरी",
    "sys:votes_received": 113
  },
  "attributions": [
    "Election Commission Nepal, २०७९ BS election results"
  ],
  "contacts": null,
  "createdAt": "2025-11-04 11:48:36.517999+00:00",
  "description": null,
  "id": "entity:person/stish-kumaar-caudhrii",
  "identifiers": null,
  "misspelledNames": null,
  "names": [
    {
      "kind": "DEFAULT",
      "lang": "ne",
      "value": "सतिश कुमार चौधरी"
    }
  ],
  "short_description": null,
  "slug": "stish-kumaar-caudhrii",
  "subType": null,
  "tags": null,
  "type": "person",
  "versionSummary": {
    "actor": {
      "id": "actor:election-importer",
      "name": "Election Results Importer",
      "slug": "election-importer"
    },
    "changeDescription": "Imported candidate result from election २०७९",
    "createdAt": "2025-11-04 11:48:36.517999+00:00",
    "entityOrRelationshipId": "entity:person/stish-kumaar-caudhrii",
    "id": "version:entity:person/stish-kumaar-caudhrii:1",
    "type": "ENTITY",
    "versionNumber": 1
  }
}