{
  "attributes": {
    "sys:address": "कास्की पोखरा महानगरपालिका जनप्रिगा मिलन मार्ग",
    "sys:age": 47,
    "sys:candidate_id": 336876,
    "sys:center_constituency_id": null,
    "sys:citizenship_district": "लमजुंग",
    "sys:district": "लमजुंग",
    "sys:district_code": 38,
    "sys:dob_bs": "2032.05.18",
    "sys:election_year": 2079,
    "sys:experience": "",
    "sys:father_name": "ट‍ेक बहादुर गुरुङ्ग",
    "sys:gender": "पुरुष",
    "sys:institute": "",
    "sys:political_party": "मंगोल नेशनल अर्गनाइजेसन",
    "sys:political_party_slug": "mngol-neshnl-argnaaijesn",
    "sys:qualification": "Education N/A",
    "sys:rank": "1",
    "sys:remarks": "",
    "sys:sc_constituency_id": "1",
    "sys:serial_no": 1688,
    "sys:spouse_name": "सरिता  गुरुङ्ग",
    "sys:state": "गण्डकी प्रदेश",
    "sys:state_code": 4,
    "sys:symbol_id": 35,
    "sys:symbol_name": "कुखुराको भाले",
    "sys:votes_received": 457
  },
  "attributions": [
    "Election Commission Nepal, २०७९ BS election results"
  ],
  "contacts": null,
  "createdAt": "2025-11-04 11:48:36.517999+00:00",
  "description": null,
  "id": "entity:person/vikaas-gurungg",
  "identifiers": null,
  "misspelledNames": null,
  "names": [
    {
      "kind": "DEFAULT",
      "lang": "ne",
      "value": "विकास गुरुङ्ग"
    }
  ],
  "short_description": null,
  "slug": "vikaas-gurungg",
  "subType": null,
  "tags": null,
  "type": "person",
  "versionSummary": {
    "actor": {
      "id": "actor:election-importer",
      "name": "Election Results Importer",
      "slug": "election-importer"
    },
    "changeDescription": "Imported candidate result from election २०७९",
    "createdAt": "2025-11-04 11:48:36.517999+00:00",
    "entityOrRelationshipId": "entity:person/vikaas-gurungg",
    "id": "version:entity:person/vikaas-gurungg:1",
    "type": "ENTITY",
    "versionNumber": 1
  }
}